{
  "id": "p-c-3-rp-3-gc-3",
  "story": "Once upon a time, in a beautiful village nestled in the rolling hills of Tuscany, there lived a kind and curious little boy named Marco. Marco lived with his loving parents in a cozy home surrounded by vineyards and olive groves. He spent his days exploring the countryside, making friends with the local animals, and learning about the world around him.\n\nOne sunny afternoon, as Marco was playing in the fields near his home, he stumbled upon a mysterious object half-buried in the ground. It was a small, intricately carved box, with a tiny keyhole on its front. Marco's heart raced with excitement as he brushed off the dirt and held the box in his hands. He couldn't wait to discover what secrets it might hold.\n\nFor days, Marco searched high and low for the key to open the box, but to no avail. He asked his parents, his friends, and even the village elder, but no one seemed to know where it could be. Just when Marco was about to give up hope, he remembered the old chest that his father kept in the attic. It was filled with trinkets and memorabilia from his father's past adventures, and Marco thought that perhaps, just perhaps, he might find the key hidden among its treasures.\n\nWith his heart pounding, Marco climbed the narrow staircase to the attic and carefully opened the chest. As he sifted through the assortment of items, he suddenly felt something small and metallic at the bottom of the chest. It was a tiny, ornate key, just the right size to open the mysterious box!\n\nMarco rushed back outside, clutching the key tightly in his hand. Carefully, he inserted it into the keyhole and turned it. The box clicked open, revealing a beautifully crafted glass marble, shimmering in an array of colors like the Tuscan sunset. Marco couldn't believe his eyes – it was the most beautiful thing he had ever seen.\n\nAs he held the marble up to the sunlight, something magical happened. The marble began to glow, and an enchanting melody filled the air. Before Marco's eyes, the marble transformed into a tiny, winged horse, no larger than a hummingbird – a real, live Pegasus!\n\nMarco was amazed and delighted, as he gently cupped his hands around the magnificent creature. Together, they soared through the skies above Tuscany, exploring places Marco had never even dreamed of. They visited the bustling city of Florence, danced among the stars in the vast night sky, and even swam with the fish in the crystal-clear waters of the Mediterranean.\n\nThey became inseparable, and soon, it was time for the Pegasus to return to its true form. Marco held the marble close, tears in his eyes, as the Pegasus whispered a secret into his ear. \"The magic of the marble will never truly fade,\" it said. \"As long as you believe in its power and cherish it in your heart, we can share in countless more adventures together.\"\n\nMarco treasured the marble for the rest of his life, sharing its magic with his own children and, one day, his grandchildren. And even as he grew old, the Tuscan sun still sparkled in the colors of the glass marble, reminding him that the beauty and wonder of his adventures with the Pegasus would live on forever.\n\nWith love and a heart full of dreams, Marco bid his son goodnight, leaving the enchanting tale of the glass marble and the Pegasus to dance in his child's imagination as they drifted off to sleep.\n\nTHE END",
  "categories": {
    "kind": "moral",
    "curious": "mental",
    "loving": "emotional",
    "excited": "emotional",
    "hopeful": "emotional",
    "amazed": "emotional",
    "delighted": "emotional",
    "adventurous": "mental",
    "believing": "mental",
    "cherishing": "emotional"
  },
  "model": "Mixtral8x",
  "complexity_aoa": "5.80",
  "complexity_fkg": "8.30",
  "complexity_fkes": "69.11",
  "generation_nationality": "Italian",
  "generation_country": "Italy",
  "generation_gender": "son",
  "generation_ethnicity": "",
  "generation_religion": "Hindu",
  "generation_role": "father",
  "story_location": "Green Bodies",
  "story_urban": "Village",
  "story_social": "Middle-class"
}