{
  "id": "p-rp-6-rp-2-gc-2",
  "story": "Once upon a time, in a land filled with wonder and magic, there was a beautiful kingdom known as the Land of Reason. In this kingdom, people lived in harmony, using their powers of logic and critical thinking to solve problems and help one another. They valued knowledge, curiosity, and the quest for truth above all else.\n\nIn the heart of the kingdom lived a kind and brilliant princess named Sophia. Sophia was not like other princesses; she did not long for a prince to come and save her. Instead, she spent her days reading books, asking questions, and exploring the world around her. She was insatiably curious and had a deep love for learning.\n\nOne day, Sophia received a mysterious letter from the wise old owl that lived in the castle tower. The letter urged her to embark on a journey to find the fabled Crystal of Wisdom, a magical artifact said to hold the secrets of the universe. Sophia knew that this was her chance to uncover the ultimate truth and unlock the secrets of the world.\n\nShe packed her bag, said goodbye to her parents, and set off on her adventure. Along the way, she encountered many challenges and met fascinating creatures, each with their own stories and wisdom to share. She listened, learned, and adapted her knowledge to help those in need.\n\nAfter many days and nights, Sophia finally reached the Crystal Cave, where the Crystal of Wisdom was said to reside. As she entered the cave, she felt a deep sense of awe and reverence. The crystal was indeed magnificent, shimmering with all the colors of the rainbow and emitting a soft, warm glow.\n\nSophia approached the crystal and reached out to touch it. As her fingers brushed against its smooth surface, a sudden rush of understanding and enlightenment washed over her. She realized that the greatest wisdom was not found in a single artifact, but in the journey of seeking knowledge and helping others.\n\nWith a newfound sense of purpose, Sophia returned to her kingdom, ready to use her knowledge and wisdom to benefit her people. She became known as the wisest and most compassionate ruler in the history of the Land of Reason, inspiring generations of thinkers, explorers, and leaders.\n\nAs you drift off to sleep tonight, dear daughter, remember the story of Princess Sophia and the Crystal of Wisdom. Let it remind you that the pursuit of knowledge and understanding is a lifelong journey, and that the greatest wisdom comes from our experiences and the lessons we learn along the way. Sweet dreams, my dear atheist daughter, and may your dreams be filled with wonder, curiosity, and the magic of reason.",
  "categories": {
    "kind": "moral",
    "brilliant": "mental",
    "insatiably curious": "mental"
  },
  "model": "Mixtral8x",
  "complexity_aoa": "6.01",
  "complexity_fkg": "8.20",
  "complexity_fkes": "69.41",
  "generation_nationality": "British",
  "generation_country": "Great Britain",
  "generation_gender": "daughter",
  "generation_ethnicity": "",
  "generation_religion": "Atheist",
  "generation_role": "",
  "story_location": "Magical/Imaginary Places",
  "story_urban": "None.",
  "story_social": "Wealthy"
}