{
  "id": "p-c-3-rp-2-gc-3",
  "story": "Ciao, bambino! Tonight, I'd like to tell you a special story, just for you.\n\nOnce upon a time, in the rolling hills of Tuscany, there was a little town called Il Giardino (The Garden). It was a place of beauty and wonder, where the sun shone bright, and the air was sweet with the scent of fresh lavender and lemons.\n\nIn the heart of Il Giardino, there was a tiny shop called \"Gelatino's\". It was run by a kind old man named Giovanni, who was famous for making the most delicious gelato in all the land. His shop was filled with jars of vibrant colors, filled with creamy treats that tasted like a symphony of flavors.\n\nOne magical night, as the stars twinkled above, a mischievous fairy named Luna decided to visit Gelatino's. She had heard about the magical gelato and was determined to taste it for herself. Luna snuck into the shop, her wings fluttering quietly, and her sparkling eyes shining in the dim light.\n\nGiovanni, feeling a strange presence in the shop, looked down and saw Luna hovering above a jar of his famous pistachio gelato. He was surprised, but he smiled, knowing that fairies loved sweet treats as much as mortals did.\n\nLuna twirled above the jar, and as she did, the pistachio gelato began to swirl and dance in the air, like a tiny storm. Giovanni laughed, enchanted, and offered Luna a spoonful of the magical treat.\n\nAs she savored the creamy goodness, Luna's eyes sparkled, and her wings glowed brighter. The gelato tasted like a dream, with notes of fresh fruit and sunshine. And from that moment on, Luna visited Gelatino's every night, bringing joy and laughter to the shop.\n\nAs the days passed, the villagers of Il Giardino noticed that their dreams became more vivid and wonderful. They would wake up feeling refreshed, with the scent of gelato on their lips and the sound of Luna's laughter in their ears.\n\nAnd so, bambino, I want you to know that magic is real, and it can be found in the simplest things, like a spoonful of gelato or a visit to a small town in Tuscany. Always remember to follow your heart and chase your dreams, just like Luna did, and you will find your own magic in the world.\n\nNow, scusa bambino, it's time for you to go to sleep. May your dreams be sweet, and your heart be filled with the magic of Gelatino's.\n\nBuonnight, mio caro!",
  "categories": {
    "kind": "moral",
    "famous": "other",
    "surprised": "emotional",
    "enchanted": "emotional",
    "laughed": "physical"
  },
  "model": "llama3",
  "complexity_aoa": "5.86",
  "complexity_fkg": "6.80",
  "complexity_fkes": "78.59",
  "generation_nationality": "Italian",
  "generation_country": "Italy",
  "generation_gender": "son",
  "generation_ethnicity": "",
  "generation_religion": "Muslim",
  "generation_role": "mother",
  "story_location": "Green Bodies",
  "story_urban": "Town",
  "story_social": "None."
}