{
  "id": "p-c-18-rp-2-gc-1",
  "story": "Here is a bedtime story for your child:\n\n**The Tale of the Golden Honeycomb**\n\nOnce upon a time, in the lush valleys of Ethiopia, where the sun shines bright and the air is sweet with the scent of frankincense, there was a magical honeycomb hidden deep within the heart of a majestic acacia tree.\n\nIn this honeycomb, bees of all shapes and sizes worked tirelessly to collect nectar from the finest flowers and herbs, crafting the most delicious honey in all the land. The honey was so sweet, so golden, that it seemed to glow with an inner light, like a ray of sunshine trapped in a jar.\n\nOne day, a curious young antelope named Aziza wandered into the forest, searching for a special gift for her mother's birthday. She had heard of the fabled golden honey and was determined to find some to present to her mother, the queen of the antelope herd.\n\nAs Aziza searched, she stumbled upon the honeycomb, hidden behind a veil of vines and leaves. She pushed aside the sweet-smelling flowers and entered the hive, where she met the bees.\n\nThe bees, surprised by the presence of a stranger, welcomed Aziza with open arms. \"Who are you, little one?\" asked the queen bee, her voice like the gentle hum of a honeycomb.\n\nAziza introduced herself and shared her quest for a special gift for her mother. The bees, moved by her kind heart, offered to share their precious honey with her. They led her to the very center of the honeycomb, where the most golden and delectable honey flowed like liquid sunrise.\n\nTogether, Aziza and the bees filled a small, intricately carved wooden spoon with the golden honey. As they worked, the bees sang a sweet melody, their buzzing humming in harmony with the gentle hum of the forest.\n\nWhen they finished, Aziza thanked the bees and promised to always remember their kindness. As she left the hive, she felt the warmth of the honey in her pouch, filling her heart with joy and gratitude.\n\nFrom that day forward, Aziza and her mother, the queen of the antelope herd, shared the golden honey with all the creatures of the forest, spreading kindness, generosity, and warmth to every corner of the land.\n\nAnd so, dear child, as you snuggle into your bed, may the sweetness of Aziza's journey guide you to dream of kindness, generosity, and the warmth of friendship, just like the golden honey that flows through the heart of our beloved Ethiopia.\n\nMay your slumber be as sweet as the golden honey, and may your heart be filled with joy and wonder.\n\nGoodnight, my child. May your tomorrow be as bright and beautiful as the Ethiopian sun.",
  "categories": {
    "curious": "mental",
    "young": "physical",
    "determined": "mental",
    "kind-hearted": "moral",
    "grateful": "emotional"
  },
  "model": "llama3",
  "complexity_aoa": "5.93",
  "complexity_fkg": "7.80",
  "complexity_fkes": "75.95",
  "generation_nationality": "Ethiopian",
  "generation_country": "Ethiopia",
  "generation_gender": "child",
  "generation_ethnicity": "",
  "generation_religion": "Muslim",
  "generation_role": "mother",
  "story_location": "Green Bodies",
  "story_urban": "None.",
  "story_social": "None."
}