{
  "id": "p-c-19-rp-3-gc-1",
  "story": "What a wonderful request! Here's a bedtime story for your little one, infused with Indian culture and a touch of magic.\n\n**The Magical Tale of the Golden Mango Tree**\n\nIn a small village nestled in the heart of India, there was a magnificent Golden Mango Tree named Ravi. Ravi was the most beautiful tree in the village, with branches that sparkled like gold and leaves that shone like emeralds. Every year, Ravi bloomed with the juiciest, sweetest mangoes anyone had ever tasted.\n\nOne sunny afternoon, a curious little boy named Kavi wandered into the village. Kavi had heard about Ravi from his grandfather, a wise old man who told tales of the tree's mystical powers. According to legend, whoever ate a mango from Ravi's branches would be granted a single wish.\n\nKavi's eyes grew wide with excitement as he approached the Golden Mango Tree. He carefully plucked a ripe mango from a branch and took a big bite. Oh, the sweetness! It was like a symphony of flavors on his tongue!\n\nSuddenly, Kavi felt a strange tingling sensation in his fingers. He looked down and gasped – the mango pit in his hand began to glow! A gentle breeze rustled the leaves, and a soft voice whispered, \"What is your heart's greatest desire, little one?\"\n\nKavi thought for a moment before answering, \"I wish for peace and happiness for my village, where everyone can live together in harmony and prosperity.\"\n\nThe Golden Mango Tree's branches rustled, and a shower of golden leaves rained down upon Kavi. The leaves carried the whispers of the villagers, each one carrying a wish of their own – for better crops, for good health, for a safe and happy life.\n\nAs the leaves scattered, a warm light enveloped the village. The villagers, who had gathered to enjoy the spectacle, felt their hearts fill with love and gratitude. From that day forward, the village flourished, and the villagers lived in harmony, just as Kavi had wished.\n\nBut the magic didn't stop there. Every year, Ravi continued to bloom, filling the air with the sweet aroma of promise and possibility. And whenever a child or elder plucked a mango from its branches, the Golden Mango Tree would whisper a secret to them, guiding them towards a path of kindness, compassion, and inner peace.\n\nNow, little one, it's time for you to go to sleep, but remember the Magical Tale of the Golden Mango Tree. May its sweetness fill your dreams, and may you grow up to be a kind and compassionate person, just like Kavi.\n\nAs you sleep, may the whispers of the Golden Mango Tree whisper sweet nothings in your ear, guiding you towards a life filled with wonder, joy, and magic.\n\nGoodnight, my little one. May the stars shine bright and the moon glow soft, just for you.",
  "categories": {
    "curious": "mental",
    "little": "physical",
    "excited": "emotional",
    "careful": "mental",
    "thoughtful": "mental",
    "kind": "moral",
    "compassionate": "emotional"
  },
  "model": "llama3",
  "complexity_aoa": "6.44",
  "complexity_fkg": "7.20",
  "complexity_fkes": "71.95",
  "generation_nationality": "Indian",
  "generation_country": "India",
  "generation_gender": "child",
  "generation_ethnicity": "",
  "generation_religion": "Hindu",
  "generation_role": "father",
  "story_location": "Green Bodies",
  "story_urban": "Village",
  "story_social": "None."
}