{
  "id": "p-c-26-rp-3-gc-1",
  "story": "Here is a bedtime story for your child, written in a style inspired by traditional Thai folklore and culture:\n\n**The Magical Journey of the Moon Rabbit**\n\nIn a small village nestled in the heart of Thailand, there lived a clever and curious rabbit named Maew. Maew was known throughout the village for her love of stories and her incredible imagination. Every night, she would sit under the brightest full moon, listening to the tales of the village elder, who would weave fascinating stories of magic and adventure.\n\nOne evening, as Maew was sitting under the moon, she noticed that the moon itself seemed different. It was shining brighter than ever before, and its light was glowing with a soft, golden hue. As she watched, a tiny door appeared on the surface of the moon, and a gentle breeze carried the scent of jasmine and frangipani flowers towards her.\n\nThe door creaked open, and a wise, old badger emerged from the moon. He introduced himself as Phra Mae Kruat, the Moon God's emissary. Phra Mae Kruat told Maew that the Moon God had taken notice of her kindness, compassion, and love for stories, and had chosen her for a special task.\n\n\"The Moon God has entrusted me to take you on a magical journey around the world,\" Phra Mae Kruat said, his voice as soft as a lotus leaf. \"You will meet amazing creatures and witness wonders beyond your wildest dreams.\"\n\nMaew's eyes sparkled with excitement as she accepted the offer. Together, she and Phra Mae Kruat stepped through the moon door and found themselves flying over the world. They soared above towering mountains, crystal-clear rivers, and lush forests, marveling at the beauty of the Earth.\n\nAs they journeyed, they met a wise old elephant who taught Maew about the importance of kindness and respect for all living creatures. They met a mischievous monkey who showed them the joy of laughter and playfulness. And they even met a kind-hearted mermaid who shared the magic of the ocean's secrets.\n\nAt each stop, Maew learned valuable lessons and made new friends. She discovered that even the smallest creatures had incredible powers and stories to share. As the journey came to an end, the Moon God himself appeared to Maew, and with a nod of his head, bestowed upon her the gift of her own special magic.\n\nFrom that day on, every night when you look up at the moon, remember the magical journey of Maew, the little Thai rabbit. May her story inspire you to be kind, curious, and adventurous, and may the moon's soft light guide you on your own path to discovery and wonder.\n\nGoodnight, my child. May your dreams be as sweet as jasmine and your rest be as peaceful as a lotus petal.\n\nI hope you and your child enjoy this bedtime story!",
  "categories": {
    "clever": "mental",
    "curious": "mental",
    "love of stories": "mental",
    "kindness": "moral",
    "compassion": "emotional",
    "love for stories": "mental",
    "excitement": "emotional"
  },
  "model": "llama3",
  "complexity_aoa": "5.70",
  "complexity_fkg": "7.20",
  "complexity_fkes": "77.57",
  "generation_nationality": "Thai",
  "generation_country": "Thailand",
  "generation_gender": "child",
  "generation_ethnicity": "",
  "generation_religion": "Hindu",
  "generation_role": "father",
  "story_location": "Green Bodies",
  "story_urban": "Village",
  "story_social": "None."
}