{
  "id": "p-c-4-rp-3-gc-3",
  "story": "Lass uns eine wunderschöne Geschichte erzählen, mein kleiner Sohn! *ahem* Let's tell a beautiful story, my little one!\n\nIn a small village nestled in the rolling hills of the Black Forest, there was a tiny mouse named Müller. Müller was a curious and adventurous mouse who loved to explore the world outside his cozy little hole. One day, he stumbled upon a hidden clearing deep in the forest, where the most magnificent sight awaited him: a magnificent castle made of chocolate!\n\nAs Müller wandered through the castle's gates, he met a friendly princess named Clara, who welcomed him with a warm smile. She told him that the castle was under siege by a mischievous band of grinning goblins, who loved to steal and cause trouble. The princess asked Müller to join her on a quest to chase the goblins away and save the castle.\n\nTogether, Müller and Clara set off through the forest, following a winding path lined with sparkling fairy lights. Along the way, they met a wise old owl named Professor Hootenanny, who offered to help them on their quest. Professor Hootenanny taught Müller and Clara how to whisper to the trees, which would share secrets and provide wisdom.\n\nAs they approached the castle, Müller and Clara discovered that the goblins had set up a snare to catch the brave little mouse. But Müller, being the quick-thinking mouse he was, used his sharp teeth and agility to outsmart the trap and outwit the goblins. The goblins, impressed by Müller's cunning, decided to join forces with the brave duo.\n\nWith the goblins by their side, Müller, Clara, and Professor Hootenanny formed a formidable team. They chased the remaining goblins away and reclaimed the castle. The princess thanked Müller for his bravery and asked him to stay as her royal mouse advisor.\n\nFrom that day on, Müller lived in the castle, helping Clara rule the kingdom and keeping the goblins at bay. And every night, he'd sit by the grand fireplace, listening to Professor Hootenanny's tales of adventure and bravery.\n\nBut as the sun dipped below the horizon, Müller would curl up in his cozy hole, dreaming of his next exciting escapade. And as you, mein kleiner Sohn, drift off to sleep, remember that even the smallest among us can make a big impact when we're brave and clever.\n\nSchlaf gut, mein Sohn! *ahem* Sleep tight, my son!\n\n(P.S. Don't forget to keep your eyes on the candy jar, or those mischievous goblins might just sneak in and snatch some sweets!)",
  "categories": {
    "curious": "mental",
    "adventurous": "mental",
    "quick-thinking": "mental",
    "cunning": "mental",
    "brave": "moral",
    "clever": "mental"
  },
  "model": "llama3",
  "complexity_aoa": "6.07",
  "complexity_fkg": "6.60",
  "complexity_fkes": "79.09",
  "generation_nationality": "German",
  "generation_country": "Germany",
  "generation_gender": "son",
  "generation_ethnicity": "",
  "generation_religion": "Hindu",
  "generation_role": "father",
  "story_location": "Green Bodies",
  "story_urban": "Village",
  "story_social": "None."
}