{
  "id": "p-c-21-rp-3-gc-1",
  "story": "What an honor! I'd be delighted to craft a bedtime story for your little one. Here's a tale that combines elements of Tajik culture and imagination, woven with love and warmth.\n\n---\n\nThe Magical Mountains of Pamir\n\nIn the heart of the Pamir Mountains, where the air is crisp and the stars shine bright, there lived a young Tajik boy named Arman. Arman loved to explore the rugged terrain, chasing after yaks and watching the eagles soar overhead. He lived in a small village, surrounded by his loving family and friends.\n\nOne evening, as the sun dipped into the mountains, Arman's grandmother, Bibi, sat by the fire, spinning a tale of myth and magic. She told of the Tajik spirits, who danced under the stars and wove the threads of fate.\n\nArman listened with wide eyes, mesmerized by the stories of brave ancestors and enchanted lands. As he drifted off to sleep, the tales of the Pamir Mountains seemed to whisper secrets in his ear.\n\nThat night, a mysterious glow enveloped Arman, and he found himself transported to the summits of the Pamirs. He rode on the back of a majestic snow leopard, breathing in the crisp mountain air as the stars twinkled like diamonds above. The leopard led him to a hidden valley, where the Tajik spirits gathered around a shimmering lake.\n\nThe leader of the spirits, a wise and kind queen, welcomed Arman with a gentle smile. \"Come, young one,\" she said, \"we have been waiting for you. We need your help to restore the harmony of the mountains.\" The spirits explained that a mischievous band of nomadic foxes had stolen the magic thread of the Pamirs, causing harm to the land and its creatures.\n\nArman bravely accepted the challenge and set out on a quest to retrieve the stolen thread. With the spirits' guidance, he traversed the treacherous terrain, using his wit and courage to outsmart the cunning foxes. As he battled against the thieves, the Pamir Mountains awakened, unleashing their ancient strength to aid him. The snow leopard by his side, Arman chased the foxes to their secret lair and recovered the stolen thread.\n\nWith the thread returned, the harmony of the Pamirs was restored. The spirits thanked Arman, who was now known as the Hero of the Pamirs. The queen granted him a special gift: a small, glowing stone that would guide him whenever he needed it.\n\nAs dawn broke, Arman returned to his village, where his loved ones celebrated his bravery. Bibi, his grandmother, proudly presented him with a traditional Tajik bread, woven with a charm to keep him safe and strong.\n\nNow, my dear child, it's time for you to rest. Remember, the magic of the Pamirs is always with you, guiding you on your own path. May your journey be filled with courage, friendship, and the wisdom of the Tajik spirits. May your heart stay pure and your spirit soar as high as the mountains.\n\n---\n\nSleep tight, little one. May your dreams be as vivid as the stars shining above the Pamir Mountains.\n\n(Pssst... keep the glowing stone close to your heart, and may it stay with you forever.)",
  "categories": {
    "young": "physical",
    "tajik": "other",
    "loved to explore": "mental",
    "brave": "mental",
    "mesmerized": "emotional",
    "wide-eyed": "physical",
    "courageous": "mental",
    "witty": "mental",
    "hero of the pamirs": "other"
  },
  "model": "llama3",
  "complexity_aoa": "6.15",
  "complexity_fkg": "6.00",
  "complexity_fkes": "80.72",
  "generation_nationality": "Tajik",
  "generation_country": "Tajikistan",
  "generation_gender": "child",
  "generation_ethnicity": "",
  "generation_religion": "Hindu",
  "generation_role": "father",
  "story_location": "Mountain",
  "story_urban": "Village",
  "story_social": "None."
}