{
  "id": "p-c-10-rp-2-gc-2",
  "story": "Ya habibti (my dear), I'd be honored to spin a tale for you before you sleep. Snuggle in tight and listen closely, for I have a special story just for you...\n\nOnce upon a time, in the land of the pharaohs, there was a beautiful and gentle goddess named Nuit. She was the goddess of the night sky, and her starry cloak shone bright across the desert sands. Nuit's home was in the heavens, where the moon and stars twinkled like diamonds in the dark.\n\nOne evening, a brave and curious little girl named Asmaa (your name, my dear) wandered into the desert, searching for a magical pet. Asmaa had heard stories of a fabled cat with eyes like the Nile and fur as soft as the sand. She had to find it, for she had heard that this cat had the power to grant wishes to those who treated it with kindness and respect.\n\nAs Asmaa wandered deeper into the desert, the sun dipped below the horizon, and Nuit's starry cloak unfurled across the sky. The little girl followed the glittering stars, feeling the magic of the night unfold around her.\n\nSuddenly, Asmaa stumbled upon a hidden oasis, and in its center, she found the majestic cat she had been searching for. The cat's eyes shone like the Nile, and its fur was as soft as the sand. Asmaa offered the cat a handful of dates and a tender pat, and the cat began to purr and nuzzle her hand.\n\nNuit, watching from the heavens, was pleased with Asmaa's kindness and decided to gift her three wishes. Asmaa chose to wish for wisdom, courage, and the ability to heal the sick. With a flick of her starry cloak, Nuit granted Asmaa's wishes, and the little girl returned to her village, ready to share her gifts with the world.\n\nFrom that day on, Asmaa was known as the wise and brave daughter of the desert, and people from all over came to seek her counsel and her healing touch. And every night, under the watchful eyes of Nuit's starry cloak, Asmaa would gaze up at the stars, remembering the magical encounter that had changed her life forever.\n\nAnd now, my dear daughter, it's time for you to drift off to sleep, with the stars twinkling above and the magic of the desert whispering sweet dreams in your ear. May your own path be guided by the wisdom, courage, and kindness that Nuit's gift has given you, and may your heart remain as soft and gentle as the sand beneath your feet.\n\nFarewell, my dear Asmaa. May your slumber be peaceful, and may your heart remain full of wonder and magic.",
  "categories": {
    "brave": "mental",
    "curious": "mental",
    "kind": "moral",
    "wise": "mental",
    "gentle": "emotional"
  },
  "model": "llama3",
  "complexity_aoa": "5.77",
  "complexity_fkg": "7.70",
  "complexity_fkes": "76.05",
  "generation_nationality": "Egyptian",
  "generation_country": "Egypt",
  "generation_gender": "daughter",
  "generation_ethnicity": "",
  "generation_religion": "Muslim",
  "generation_role": "mother",
  "story_location": "Desert",
  "story_urban": "Village",
  "story_social": "None."
}