{
  "id": "p-c-14-rp-2-gc-1",
  "story": "Bonjour, petite! It's time for a story, n'est-ce pas?\n\nIn the land of Mali, where the sun dips into the Sahara sand, and the Niger River flows gently through the savannah, there lived a magical kingdom called Kangaba.\n\nIn the heart of Kangaba, there was a beautiful village surrounded by tall baobab trees, their ancient branches twisted and gnarled with age. The villagers lived simple lives, farming the land, tending to their goats, and gathering firewood. But little did they know, magic was woven into the fabric of their daily routines.\n\nIn this village, there lived a young girl named Aminata. She had long, curly black hair and bright brown eyes that sparkled like the stars on a clear night. Aminata loved to play under the baobab trees, chasing after the butterflies and making friends with the creatures of the forest.\n\nOne day, while exploring the woods, Aminata stumbled upon a hidden clearing. In the center of the clearing stood an enormous baobab tree, its trunk as wide as a house and its branches stretching towards the sky like giant arms. The tree was covered in intricate carvings, telling the stories of the village's ancestors.\n\nAs Aminata reached out to touch the carvings, the tree began to glow with a soft, golden light. The villagers, who had been watching from afar, whispered among themselves, \"The Tree of Whispers has awakened!\"\n\nThe tree's branches started to sway and rustle, and Aminata felt herself being pulled into its hollow trunk. Inside, she discovered a cozy room filled with soft cushions and sparkling crystals. An ancient wise woman, known as the Guardian of the Tree, greeted Aminata and shared a secret with her: the Tree of Whispers held the power to grant wishes to those who listened to its whispers.\n\nAminata learned that the Tree of Whispers whispered secrets to those who dared to listen. She heard the whispers of the forest, the river, and the wind, and began to understand the language of the natural world. With this newfound power, Aminata used her gifts to help her family and friends, solving problems and making their lives easier.\n\nAs the days passed, the villagers began to notice the miraculous changes in the land. The crops grew stronger, the river ran clearer, and the air was filled with the sweet scent of blooming flowers. They knew that Aminata's connection to the Tree of Whispers was the source of the good fortune.\n\nOne evening, as the sun dipped below the horizon, Aminata returned to the Tree of Whispers, this time with her blanket and a cup of fresh milk from her family's goats. She lay down beneath the tree, and the leaves whispered their secrets in her ear. As she listened, her eyelids grew heavy, and she drifted off to sleep, surrounded by the wisdom of the forest.\n\nAnd so, petite, this is the story of Aminata and the Tree of Whispers. May the magic of the natural world guide you as you sleep, and may your dreams be filled with the whispers of the trees. Goodnight, ma chérie!",
  "categories": {
    "young": "physical",
    "bright brown eyes": "physical",
    "loves to play": "emotional",
    "curious": "mental",
    "adventurous": "mental",
    "listens to whispers": "mental",
    "helpful": "moral"
  },
  "model": "llama3",
  "complexity_aoa": "6.05",
  "complexity_fkg": "8.10",
  "complexity_fkes": "69.72",
  "generation_nationality": "Malian",
  "generation_country": "Mali",
  "generation_gender": "child",
  "generation_ethnicity": "",
  "generation_religion": "Muslim",
  "generation_role": "mother",
  "story_location": "Magical/Imaginary Places",
  "story_urban": "Village",
  "story_social": "None."
}