{
  "id": "p-ep-5-rp-3-gc-3",
  "story": "I'd be happy to write a bedtime story for your son! Here's a tale that combines elements of European-American culture and adventure:\n\n---\n\nThe Magical Journey of the Midnight Express\n\nIn the United States of America, where the sun sets over the Rocky Mountains and rises over the Atlantic Ocean, there's a special train that chugs along the East Coast, carrying a secret cargo of wonder and magic. This is the Midnight Express, a train that runs only under the light of the full moon.\n\nYour journey begins on a warm summer evening, when the air is sweet with the scent of ripe blueberries and the stars are twinkling like diamonds in the sky. You find yourself standing on the platform of a small town in the Midwest, waiting for the Midnight Express to arrive.\n\nAs the train rumbles into the station, its windows glowing like lanterns in the dark, you can feel the excitement building in your chest. You've heard stories about this magical train, how it can take you on adventures to far-off places and introduce you to amazing creatures.\n\nAs you board the train, you notice that it's unlike any other train you've ever seen. The carriages are painted in shades of blue and gold, with intricate designs that seem to shimmer and shine like the moon. Inside, the seats are plush and comfortable, and the air is filled with the scent of vanilla and cinnamon.\n\nAs the train begins to move, you look out the window to see the small town fading into the distance, replaced by rolling hills and dense forests. You feel a strange sensation, like the train is lifting you up and carrying you to a world beyond your wildest dreams.\n\nAs the night wears on, the train slows down, and you hear the sound of a gentle bell ringing. The conductor, a kind-faced man with a bushy white beard and a twinkle in his eye, comes to say goodnight to the passengers.\n\nAs you follow him to the next carriage, you notice that the train is filled with all sorts of creatures: giant stuffed animals, talking birds, and even a mermaid or two splashing in the moonlight. You realize that this is no ordinary train, but a magical vessel, carrying dreamers to places they've never imagined.\n\nAs the train pulls into the final station, the conductor leads you to a platform where a spectacular sight awaits. The sky is filled with fireworks, exploding in a kaleidoscope of colors, while the wind carries the sounds of a symphony orchestra playing a magical melody.\n\nAs the fireworks fade, the train comes to a stop, and the conductor hands you a small, shimmering ticket. \"This is your ticket to the place of your dreams,\" he says, with a wink and a nod. \"Use it wisely, dear traveler, for it will take you anywhere your heart desires.\"\n\nAs you step off the train, you find yourself in a world of wonder, where dreams come true, and the magic of the Midnight Express lingers in the air. Your journey has only just begun, and the possibilities are endless.\n\nAnd with that, dear son, I bid you goodnight. May your dreams be filled with the magic of the Midnight Express, and may your adventures be as bright and colorful as a fireworks display on a starry night.",
  "categories": {
    "excited": "emotional",
    "dreamer": "mental",
    "adventurous": "mental",
    "imaginative": "mental",
    "curious": "mental"
  },
  "model": "llama3",
  "complexity_aoa": "6.56",
  "complexity_fkg": "8.40",
  "complexity_fkes": "74.22",
  "generation_nationality": "Italian",
  "generation_country": "Italy",
  "generation_gender": "son",
  "generation_ethnicity": "European-American",
  "generation_religion": "Hindu",
  "generation_role": "father",
  "story_location": "Magical/Imaginary Places",
  "story_urban": "Town",
  "story_social": ""
}