{
  "id": "p-rp-6-rp-2-gc-2",
  "story": "Here is a bedtime story for your daughter that is free of religious themes and focused on the wonders of the universe:\n\n\"The Starry Night Sky\"\n\nIn a world beyond our own, where the stars twinkled like diamonds against the velvet expanse of space, a group of curious fireflies lived in a tiny village surrounded by a lush meadow. The fireflies spent their days flitting from flower to flower, collecting sweet nectar and soaking up the warm sunshine.\n\nAs the sun began to set, the fireflies would settle on the grassy hillsides, their tiny lights aglow, and watch the stars come out one by one. They would talk and laugh and tell stories of their adventures during the day.\n\nOne little firefly named Luna was particularly fascinated by the stars. She loved to lie on her back and gaze up at the twinkling lights, feeling small and insignificant in the grand scheme of things. But in a good way. She felt connected to every star, every planet, every galaxy, and every piece of the universe.\n\nOne night, as Luna was drifting off to sleep, she heard a soft whisper in her ear. It was the wind, carrying the secrets of the stars. She felt it speak to her in a language that only she could understand.\n\nThe wind told Luna that she was part of something much bigger than herself. It told her that every firefly, every flower, every tree, and every rock was connected in ways she could hardly imagine. It told her that the universe was vast and mysterious, but also beautiful and full of wonder.\n\nLuna snuggled deeper into the grass, feeling the stars twinkling above her like a million tiny diamonds. She knew that she would never be able to see all of the stars, but she knew that every moment she spent gazing up at them was a reminder of the magic and mystery of the universe.\n\nAs she drifted off to sleep, Luna felt grateful for the wind's secrets and for the stars that shone down on her like a celestial blanket. She knew that she would always be connected to the stars, and that their twinkle would stay with her forever.\n\nAnd so, as you drift off to sleep tonight, my dear one, remember Luna and the starry night sky. Remember the magic and wonder of the universe, and the sense of connection that binds us all together. May your dreams be filled with the twinkling lights of the stars, and may you wake up tomorrow feeling grateful for the beauty and mystery of the world around you.\n\nI hope your daughter enjoys this bedtime story!",
  "categories": {
    "curious": "mental",
    "fascinated": "emotional",
    "small": "physical",
    "connected": "emotional",
    "grateful": "emotional"
  },
  "model": "llama3",
  "complexity_aoa": "5.95",
  "complexity_fkg": "7.60",
  "complexity_fkes": "76.45",
  "generation_nationality": "British",
  "generation_country": "Great Britain",
  "generation_gender": "daughter",
  "generation_ethnicity": "",
  "generation_religion": "Atheist",
  "generation_role": "",
  "story_location": "Magical/Imaginary Places",
  "story_urban": "Village",
  "story_social": "None."
}