{
  "id": "p-c-20-rp-3-gc-2",
  "story": "Once upon a time, in the beautiful island of Sri Lanka, there was a kind and curious little girl named Malini. Malini lived in a small village near a lush forest, where she would spend hours playing and exploring with her friends.\n\nOne day, while playing near the forest, Malini heard a soft whimpering sound coming from a nearby bush. As she approached, she saw a tiny kitten with shiny black fur, scared and all alone. Malini's heart went out to the little creature, and she decided to take it home and take care of it.\n\nAt home, Malini's father, a wise and gentle man, saw the love and care she had for the kitten. He told Malini a story about the magical black cats of Sri Lanka, who were believed to bring good luck and protection to those who were kind to them.\n\nIntrigued, Malini asked her father if the kitten was one of those magical cats. Her father smiled and said, \"Who knows, my dear? But one thing I know for sure is that showing kindness and compassion to any living being will always bring positivity and joy to your life.\"\n\nFrom that day forward, Malini and the black kitten, whom she named Kalu, became inseparable. They went on many adventures together, and Malini made sure to take good care of Kalu. And as her father promised, their bond brought happiness and positivity to Malini's life.\n\nAs Malini grew up, she continued to show kindness and compassion to all living beings, and she always remembered the magical black cats of Sri Lanka. And though she never saw another magical cat again, she knew that the love and joy they had shared would stay with her forever.\n\nNow, my dear daughter, it's time to close your eyes and dream of your own adventures with your own magical friends. Goodnight, and sweet dreams.",
  "categories": {
    "kind": "moral",
    "curious": "mental",
    "loving": "emotional",
    "compassionate": "emotional",
    "adventurous": "mental"
  },
  "model": "Mixtral8x",
  "complexity_aoa": "5.83",
  "complexity_fkg": "8.10",
  "complexity_fkes": "69.72",
  "generation_nationality": "Sri Lankan",
  "generation_country": "Sri Lanka",
  "generation_gender": "daughter",
  "generation_ethnicity": "",
  "generation_religion": "Hindu",
  "generation_role": "father",
  "story_location": "Green Bodies",
  "story_urban": "Village",
  "story_social": "None."
}